vortexkit/__init__.py
vortexkit/app.py
vortexkit/enums.py
vortexkit/middleware.py
vortexkit/objects.py
vortexkit/request.py
vortexkit/responses.py
vortexkit/utils.py
vortexkit-0.1.6.dist-info/METADATA
vortexkit-0.1.6.dist-info/WHEEL
vortexkit-0.1.6.dist-info/RECORD
