Metadata-Version: 2.1
Name: VortexKit
Version: 0.1.6
Summary: A lightweight, customizable WSGI framework designed to handle web requests with ease and flexibility.
Author: dafty144
Author-email: contact@leojohnston.tech
Requires-Python: >=3.10,<4.0
Classifier: Programming Language :: Python :: 3
Classifier: Programming Language :: Python :: 3.10
Classifier: Programming Language :: Python :: 3.11
Classifier: Programming Language :: Python :: 3.12
